cazoo_cloudwatch_events/__init__.py
cazoo_cloudwatch_events/events.py
cazoo_cloudwatch_events-0.1.12.dist-info/LICENSE.txt
cazoo_cloudwatch_events-0.1.12.dist-info/METADATA
cazoo_cloudwatch_events-0.1.12.dist-info/WHEEL
cazoo_cloudwatch_events-0.1.12.dist-info/top_level.txt
cazoo_cloudwatch_events-0.1.12.dist-info/RECORD
